{
   "abstract" : "file is older? oldest? is newer? newest? similar? the same?",
   "author" : [
      "Jozef Kutej <jkutej@cpan.org>"
   ],
   "dynamic_config" : 1,
   "generated_by" : "Module::Build version 0.4214",
   "keywords" : [
      "file",
      "stat"
   ],
   "license" : [
      "perl_5"
   ],
   "meta-spec" : {
      "url" : "http://search.cpan.org/perldoc?CPAN::Meta::Spec",
      "version" : "2"
   },
   "name" : "File-is",
   "prereqs" : {
      "build" : {
         "requires" : {
            "File::Path" : "0",
            "File::Temp" : "0",
            "Test::Exception" : "0",
            "Test::More" : "0"
         }
      },
      "configure" : {
         "requires" : {
            "Module::Build" : "0.3607"
         }
      },
      "runtime" : {
         "requires" : {
            "Carp" : "0",
            "File::Spec" : "0"
         }
      }
   },
   "provides" : {
      "File::is" : {
         "file" : "lib/File/is.pm",
         "version" : "0.04"
      }
   },
   "release_status" : "stable",
   "resources" : {
      "bugtracker" : {
         "web" : "http://github.com/jozef/File-is/issues"
      },
      "license" : [
         "http://dev.perl.org/licenses/"
      ],
      "repository" : {
         "url" : "http://github.com/jozef/File-is"
      }
   },
   "version" : "0.04",
   "x_serialization_backend" : "JSON::PP version 2.27300"
}
