{"version":130003,"stmts":[{"stmt":{"InsertStmt":{"relation":{"relname":"insertconflicttest","inh":true,"relpersistence":"p","location":12},"selectStmt":{"SelectStmt":{"valuesLists":[{"List":{"items":[{"A_Const":{"val":{"Integer":{"ival":1}},"location":40}},{"A_Const":{"val":{"String":{"str":"Apple"}},"location":43}}]}},{"List":{"items":[{"A_Const":{"val":{"Integer":{"ival":2}},"location":56}},{"A_Const":{"val":{"String":{"str":"Orange"}},"location":59}}]}}],"limitOption":"LIMIT_OPTION_DEFAULT","op":"SETOP_NONE"}},"onConflictClause":{"action":"ONCONFLICT_UPDATE","infer":{"indexElems":[{"IndexElem":{"name":"key","ordering":"SORTBY_DEFAULT","nulls_ordering":"SORTBY_NULLS_DEFAULT"}}],"location":82},"targetList":[{"ResTarget":{"name":"fruit","val":{"MultiAssignRef":{"source":{"RowExpr":{"args":[{"ColumnRef":{"fields":[{"String":{"str":"excluded"}},{"String":{"str":"fruit"}}],"location":123}},{"ColumnRef":{"fields":[{"String":{"str":"excluded"}},{"String":{"str":"key"}}],"location":139}}],"row_format":"COERCE_IMPLICIT_CAST","location":121}},"colno":1,"ncolumns":2}},"location":106}},{"ResTarget":{"name":"key","val":{"MultiAssignRef":{"source":{"RowExpr":{"args":[{"ColumnRef":{"fields":[{"String":{"str":"excluded"}},{"String":{"str":"fruit"}}],"location":123}},{"ColumnRef":{"fields":[{"String":{"str":"excluded"}},{"String":{"str":"key"}}],"location":139}}],"row_format":"COERCE_IMPLICIT_CAST","location":121}},"colno":2,"ncolumns":2}},"location":113}}],"location":70},"override":"OVERRIDING_NOT_SET"}}}]}