{"dist":"Rose-DB-0.786","version":"0.786","provides":{"Rose::DB::Constants":{"file":"lib/Rose/DB/Constants.pm"},"Rose::DB::Generic":{"file":"lib/Rose/DB/Generic.pm","version":"0.11"},"Rose::DB":{"file":"lib/Rose/DB.pm","version":"0.786"},"Rose::DB::Registry":{"file":"lib/Rose/DB/Registry.pm","version":"0.728"},"Rose::DB::SQLite":{"file":"lib/Rose/DB/SQLite.pm","version":"0.765"},"Rose::DB::Cache::Entry":{"version":"0.736","file":"lib/Rose/DB/Cache/Entry.pm"},"Rose::DB::Registry::Entry":{"version":"0.784","file":"lib/Rose/DB/Registry/Entry.pm"},"Rose::DB::Oracle":{"version":"0.784","file":"lib/Rose/DB/Oracle.pm"},"Rose::DB::MySQL":{"file":"lib/Rose/DB/MySQL.pm","version":"0.774"},"Rose::DB::Cache":{"version":"0.755","file":"lib/Rose/DB/Cache.pm"},"Rose::DB::Pg":{"file":"lib/Rose/DB/Pg.pm","version":"0.786"},"Rose::DB::Oracle::DateHandler":{"file":"lib/Rose/DB/Oracle.pm","version":"0.784"},"Rose::DateTime::Format::Generic":{"file":"lib/Rose/DB.pm","version":"0.786"},"Rose::DB::MariaDB":{"version":"0.780","file":"lib/Rose/DB/MariaDB.pm"},"Rose::DB::Informix":{"version":"0.774","file":"lib/Rose/DB/Informix.pm"}},"pathname":"J/JS/JSIRACUSA/Rose-DB-0.786.tar.gz","name":"Rose::DB","target":"Rose::DB"}