{
   "abstract" : "queue that can be shared across processes",
   "author" : [
      "Marty O'Brien <mob@cpan.org>"
   ],
   "dynamic_config" : 1,
   "generated_by" : "ExtUtils::MakeMaker version 7.34, CPAN::Meta::Converter version 2.150005",
   "license" : [
      "perl_5"
   ],
   "meta-spec" : {
      "url" : "http://search.cpan.org/perldoc?CPAN::Meta::Spec",
      "version" : "2"
   },
   "name" : "Forks-Queue",
   "no_index" : {
      "directory" : [
         "t",
         "inc"
      ]
   },
   "prereqs" : {
      "build" : {
         "requires" : {
            "ExtUtils::MakeMaker" : "0"
         }
      },
      "configure" : {
         "requires" : {
            "ExtUtils::MakeMaker" : "0"
         }
      },
      "runtime" : {
         "recommends" : {
            "DBD::SQLite" : "0",
            "DBI" : "0"
         },
         "requires" : {
            "File::Temp" : "0",
            "JSON" : "2.0",
            "Time::HiRes" : "0"
         }
      }
   },
   "release_status" : "stable",
   "version" : "0.11",
   "x_serialization_backend" : "JSON::PP version 2.27400"
}
