{"version":1.02,"target":"XML::SAX","name":"XML::SAX","provides":{"XML::SAX::DocumentLocator":{"file":"lib/XML/SAX/DocumentLocator.pm"},"XML::SAX::PurePerl::Productions":{"file":"lib/XML/SAX/PurePerl/Productions.pm"},"XML::SAX":{"file":"lib/XML/SAX.pm","version":1.02},"XML::SAX::PurePerl":{"version":1.02,"file":"lib/XML/SAX/PurePerl.pm"},"XML::SAX::PurePerl::Exception":{"file":"lib/XML/SAX/PurePerl/Exception.pm"},"XML::SAX::PurePerl::DebugHandler":{"file":"lib/XML/SAX/PurePerl/DebugHandler.pm"},"XML::SAX::ParserFactory":{"version":1.02,"file":"lib/XML/SAX/ParserFactory.pm"},"XML::SAX::PurePerl::Reader::Stream":{"file":"lib/XML/SAX/PurePerl/Reader/Stream.pm"},"XML::SAX::PurePerl::Reader::URI":{"file":"lib/XML/SAX/PurePerl/Reader/URI.pm"},"XML::SAX::PurePerl::Reader::String":{"file":"lib/XML/SAX/PurePerl/Reader/String.pm"},"XML::SAX::PurePerl::Reader":{"file":"lib/XML/SAX/PurePerl/Reader.pm"}},"pathname":"G/GR/GRANTM/XML-SAX-1.02.tar.gz","dist":"XML-SAX-1.02"}