<msg><src>CC128-v0.11</src><dsb>00596</dsb><time>13:10:30</time><hist><dsw>00597</dsw><type>1</type><units>kwhr</units><data><sensor>0</sensor><h290>4.543</h290><h288>2.681</h288><h286>1.936</h286><h284>2.167</h284></data><data><sensor>1</sensor><h290>0.000</h290><h288>0.000</h288><h286>0.000</h286><h284>0.000</h284></data><data><sensor>2</sensor><h290>0.000</h290><h288>0.000</h288><h286>0.000</h286><h284>0.000</h284></data><data><sensor>3</sensor><h290>0.000</h290><h288>0.000</h288><h286>0.000</h286><h284>0.000</h284></data><data><sensor>4</sensor><h290>0.000</h290><h288>0.000</h288><h286>0.000</h286><h284>0.000</h284></data><data><sensor>5</sensor><h290>0.000</h290><h288>0.000</h288><h286>0.000</h286><h284>0.000</h284></data><data><sensor>6</sensor><h290>0.000</h290><h288>0.000</h288><h286>0.000</h286><h284>0.000</h284></data><data><sensor>7</sensor><h290>0.000</h290><h288>0.000</h288><h286>0.000</h286><h284>0.000</h284></data><data><sensor>8</sensor><h290>0.000</h290><h288>0.000</h288><h286>0.000</h286><h284>0.000</h284></data><data><sensor>9</sensor><h290>0.000</h290><h288>0.000</h288><h286>0.000</h286><h284>0.000</h284></data></hist></msg>
