{
   "abstract" : "unknown",
   "author" : [
      "Eto Demerzel <eto.demerzel@usrobots.com>"
   ],
   "dynamic_config" : 1,
   "generated_by" : "ExtUtils::MakeMaker version 6.98, CPAN::Meta::Converter version 2.142060",
   "license" : [
      "unknown"
   ],
   "meta-spec" : {
      "url" : "http://search.cpan.org/perldoc?CPAN::Meta::Spec",
      "version" : "2"
   },
   "name" : "Math-Int64-C_API-Sample",
   "no_index" : {
      "directory" : [
         "t",
         "inc"
      ]
   },
   "prereqs" : {
      "build" : {
         "requires" : {
            "ExtUtils::MakeMaker" : "0"
         }
      },
      "configure" : {
         "requires" : {
            "ExtUtils::MakeMaker" : "0"
         }
      },
      "runtime" : {
         "requires" : {
            "Math::Int64" : "0.34"
         }
      }
   },
   "release_status" : "stable",
   "version" : "0.09"
}
