{
   "abstract" : "The Apache protection module part of Lemonldap::NG Web-SSO system.",
   "author" : [
      "Xavier Guimard <x.guimard@free.fr>"
   ],
   "dynamic_config" : 1,
   "generated_by" : "ExtUtils::MakeMaker version 7.24, CPAN::Meta::Converter version 2.150010",
   "license" : [
      "open_source"
   ],
   "meta-spec" : {
      "url" : "http://search.cpan.org/perldoc?CPAN::Meta::Spec",
      "version" : "2"
   },
   "name" : "Lemonldap-NG-Handler",
   "no_index" : {
      "directory" : [
         "t",
         "inc"
      ]
   },
   "prereqs" : {
      "build" : {
         "requires" : {
            "Cwd" : "0",
            "Digest::HMAC_SHA1" : "0",
            "File::Basename" : "0",
            "HTTP::Message" : "0",
            "IO::Pipe" : "0",
            "SOAP::Lite" : "0",
            "Test::MockObject" : "0",
            "Test::Pod" : "0"
         }
      },
      "configure" : {
         "requires" : {
            "ExtUtils::MakeMaker" : "0"
         }
      },
      "runtime" : {
         "recommends" : {
            "Cache::Memcached" : "0",
            "Digest::HMAC_SHA1" : "0",
            "HTTP::Message" : "0",
            "LWP::Protocol::https" : "0",
            "SOAP::Lite" : "0"
         },
         "requires" : {
            "Apache::Session::Generate::MD5" : "0",
            "CGI" : "3.08",
            "LWP" : "0",
            "Lemonldap::NG::Common" : "v1.9.18",
            "Mouse" : "0",
            "URI" : "0"
         }
      }
   },
   "release_status" : "stable",
   "version" : "v1.9.18",
   "x_serialization_backend" : "JSON::PP version 2.27400_02"
}
