{
   "abstract" : "manage security headers with many safe defaults",
   "author" : [
      "kfly8 <kfly@cpan.org>"
   ],
   "dynamic_config" : 0,
   "generated_by" : "Minilla/v3.1.25",
   "license" : [
      "perl_5"
   ],
   "meta-spec" : {
      "url" : "http://search.cpan.org/perldoc?CPAN::Meta::Spec",
      "version" : "2"
   },
   "name" : "HTTP-SecureHeaders",
   "no_index" : {
      "directory" : [
         "t",
         "xt",
         "inc",
         "share",
         "eg",
         "examples",
         "author",
         "builder"
      ]
   },
   "prereqs" : {
      "configure" : {
         "requires" : {
            "Module::Build::Tiny" : "0.035"
         }
      },
      "develop" : {
         "requires" : {
            "Test::CPAN::Meta" : "0",
            "Test::MinimumVersion::Fast" : "0.04",
            "Test::PAUSE::Permissions" : "0.07",
            "Test::Pod" : "1.41",
            "Test::Spellunker" : "v0.2.7"
         }
      },
      "runtime" : {
         "requires" : {
            "perl" : "5.014000"
         }
      },
      "test" : {
         "requires" : {
            "Test2::V0" : "0.000147"
         }
      }
   },
   "provides" : {
      "HTTP::SecureHeaders" : {
         "file" : "lib/HTTP/SecureHeaders.pm",
         "version" : "0.02"
      }
   },
   "release_status" : "stable",
   "resources" : {
      "bugtracker" : {
         "web" : "https://github.com/kfly8/p5-HTTP-SecureHeaders/issues"
      },
      "homepage" : "https://github.com/kfly8/p5-HTTP-SecureHeaders",
      "repository" : {
         "type" : "git",
         "url" : "https://github.com/kfly8/p5-HTTP-SecureHeaders.git",
         "web" : "https://github.com/kfly8/p5-HTTP-SecureHeaders"
      }
   },
   "version" : "0.02",
   "x_authority" : "cpan:KFLY",
   "x_contributors" : [
      "kobaken <kentafly88@gmail.com>"
   ],
   "x_serialization_backend" : "JSON::PP version 4.16",
   "x_static_install" : 1
}
