{
   "abstract" : "Manipulate Google Finance portfolios a little",
   "author" : [
      "Gryphon Shafer <gryphon@cpan.org>"
   ],
   "dynamic_config" : 0,
   "generated_by" : "Dist::Zilla version 6.032, CPAN::Meta::Converter version 2.150010",
   "license" : [
      "artistic_2"
   ],
   "meta-spec" : {
      "url" : "http://search.cpan.org/perldoc?CPAN::Meta::Spec",
      "version" : 2
   },
   "name" : "Finance-Google-Portfolio",
   "prereqs" : {
      "configure" : {
         "requires" : {
            "ExtUtils::MakeMaker" : "0",
            "perl" : "5.010"
         }
      },
      "develop" : {
         "requires" : {
            "Pod::Coverage::TrustPod" : "0",
            "Software::Security::Policy::Individual" : "0",
            "Test::EOL" : "0",
            "Test::Kwalitee" : "1.21",
            "Test::More" : "0.88",
            "Test::NoTabs" : "0",
            "Test::Pod" : "1.41",
            "Test::Pod::Coverage" : "1.08",
            "Test::Portability::Files" : "0",
            "Test::Synopsis" : "0"
         }
      },
      "runtime" : {
         "requires" : {
            "Carp" : "0",
            "HTML::Form" : "0",
            "JSON::PP" : "0",
            "LWP::UserAgent" : "0",
            "Moo" : "0",
            "URI" : "0",
            "namespace::clean" : "0",
            "perl" : "5.010",
            "strict" : "0",
            "warnings" : "0"
         }
      },
      "test" : {
         "requires" : {
            "File::Spec" : "0",
            "IO::Handle" : "0",
            "IPC::Open3" : "0",
            "Test2::V0" : "0",
            "Test::More" : "0",
            "perl" : "5.010"
         }
      }
   },
   "release_status" : "stable",
   "resources" : {
      "bugtracker" : {
         "web" : "https://github.com/gryphonshafer/Finance-Google-Portfolio/issues"
      },
      "homepage" : "https://github.com/gryphonshafer/Finance-Google-Portfolio",
      "repository" : {
         "type" : "git",
         "url" : "https://github.com/gryphonshafer/Finance-Google-Portfolio.git",
         "web" : "https://github.com/gryphonshafer/Finance-Google-Portfolio"
      }
   },
   "version" : "1.08",
   "x_generated_by_perl" : "v5.40.2",
   "x_serialization_backend" : "Cpanel::JSON::XS version 4.39",
   "x_spdx_expression" : "Artistic-2.0"
}

